{
    "id": "0178a3ab-d163-0000-4b55-bceadebb03fa",
    "name": "Hogflix Movies",
    "created_at": "2021-04-05T20:14:09.763753Z",
    "updated_at": "2021-04-05T20:14:25.443181Z",
    "membership_level": 15,
    "plugins_access_level": 9,
    "teams": [
        {
            "id": 2,
            "uuid": "0178a3ab-d1e5-0000-c5ca-da746c68f506",
            "organization": "0178a3ab-d163-0000-4b55-bceadebb03fa",
            "api_token": "tJy-b6mTLwvNP_ZJHrfgn99pQCYOGFE3-nwpb8utFa8",
            "name": "Hogflix Demo App",
            "completed_snippet_onboarding": true,
            "ingested_event": true,
            "is_demo": true,
            "timezone": "Europe/Kiev"
        }
    ],
    "available_product_features": []
}
