{
  "db_name": "PostgreSQL",
  "query": "\n        SELECT destination\n        FROM posthog_shortlink\n        WHERE origin_key = $1 AND origin_domain = $2\n        ",
  "describe": {
    "columns": [
      {
        "ordinal": 0,
        "name": "destination",
        "type_info": "Varchar"
      }
    ],
    "parameters": {
      "Left": [
        "Text",
        "Text"
      ]
    },
    "nullable": [
      false
    ]
  },
  "hash": "2a33238f0e24e57890eb2976d7844138a62e154175a2dddabe64718e2a14fa7d"
}
