{
  "db_name": "PostgreSQL",
  "query": "\n        INSERT INTO posthog_cohortpeople (person_id, cohort_id, version)\n        SELECT pid, $1, $3\n        FROM UNNEST($2::bigint[]) AS t(pid)\n        WHERE NOT EXISTS (\n            SELECT 1 FROM posthog_cohortpeople cp\n            WHERE cp.person_id = pid AND cp.cohort_id = $1\n        )\n        ON CONFLICT DO NOTHING\n        ",
  "describe": {
    "columns": [],
    "parameters": {
      "Left": [
        "Int4",
        "Int8Array",
        "Int4"
      ]
    },
    "nullable": []
  },
  "hash": "1094540dc7145671df1ee86bfa3f642d32c375fc398874750593ee943c1aefa9"
}
